CHANGELOG.md
CONTRIBUTING.md
LICENSE.md
README.md
docs/conf.py
docs/deploy.md
docs/index.rst
tests/__init__.py
tests/conftest.py
tests/test_yager.py
tox.ini
yager/__init__.py
yager/controllers/__init__.py
yager/controllers/base.py
yager/core/__init__.py
yager/core/exc.py
yager/core/hooks.py
yager/core/log.py
yager/core/version.py
yager/ext/__init__.py
yager/main.py
yager/templates/__init__.py
yager/templates/output_csv.j2
yager-0.1.0.dist-info/entry_points.txt
yager-0.1.0.dist-info/LICENSE.md
yager-0.1.0.dist-info/WHEEL
yager-0.1.0.dist-info/METADATA
yager-0.1.0.dist-info/RECORD
