Metadata-Version: 2.1
Name: yager
Version: 0.1.0
Summary: Yet Another GEneric Reporter tool for parsing of XML data into an SQLite database and subsequent universal reporting based on SQL queries and Jinja2 templates.
Home-page: https://github.com/undp/yager
License: MIT
Keywords: CLI,XML,SQL,SQLite,Jinja2,template,parsing,reporting
Author: Oleksiy Kuzmenko
Author-email: oleksiy.kuzmenko@undp.org
Requires-Python: >=3.6.1,<4.0.0
Classifier: Development Status :: 4 - Beta
Classifier: Environment :: Console
Classifier: Intended Audience :: System Administrators
Classifier: License :: OSI Approved :: MIT License
Classifier: Natural Language :: English
Classifier: Operating System :: POSIX :: Linux
Classifier: Programming Language :: Python :: 3
Classifier: Programming Language :: Python :: 3 :: Only
Classifier: Programming Language :: Python :: 3.6
Classifier: Programming Language :: Python :: 3.7
Classifier: Programming Language :: Python :: 3.8
Classifier: Programming Language :: Python :: 3.9
Classifier: Topic :: Utilities
Provides-Extra: code-format
Provides-Extra: code-lint
Provides-Extra: docs
Provides-Extra: test
Requires-Dist: black (>=19.10b0,<20.0); extra == "code-format"
Requires-Dist: blacken-docs (>=1.7,<2.0); extra == "code-format"
Requires-Dist: cement (>=3.0.4,<4.0.0)
Requires-Dist: colorlog (>=4.2.1,<5.0.0)
Requires-Dist: flake8 (>=3.8,<4.0); extra == "code-lint"
Requires-Dist: flake8-bandit (>=2.1,<3.0); extra == "code-lint"
Requires-Dist: flake8-blind-except (>=0.1,<0.2); extra == "code-lint"
Requires-Dist: flake8-bugbear (>=20.1,<21.0); extra == "code-lint"
Requires-Dist: flake8-builtins (>=1.5,<2.0); extra == "code-lint"
Requires-Dist: flake8-docstrings (>=1.5,<2.0); extra == "code-lint"
Requires-Dist: flake8-import-order (>=0.18,<0.19); extra == "code-lint"
Requires-Dist: flake8-logging-format (>=0.6,<0.7); extra == "code-lint"
Requires-Dist: flake8-mypy (>=17.8,<18.0); extra == "code-lint"
Requires-Dist: jinja2 (>=2.11.2,<3.0.0)
Requires-Dist: pep8-naming (>=0.8,<0.9); extra == "code-lint"
Requires-Dist: pygments (>=2.6,<3.0); extra == "code-lint"
Requires-Dist: pytest (>=6.0,<7.0); extra == "test"
Requires-Dist: pytest-benchmark[aspect] (>=3.2,<4.0); extra == "test"
Requires-Dist: pytest-cov (>=2.10,<3.0); extra == "test"
Requires-Dist: pytest-instafail (>=0.4,<0.5); extra == "test"
Requires-Dist: pytest-lazy-fixture (>=0.6,<0.7); extra == "test"
Requires-Dist: pytest-random-order (>=1.0,<2.0); extra == "test"
Requires-Dist: pyyaml (>=5.3.1,<6.0.0)
Requires-Dist: recommonmark (>=0.6.0,<0.7.0); extra == "docs"
Requires-Dist: sphinx (>=3.1,<4.0); extra == "docs"
Requires-Dist: sphinx-autodoc-typehints (>=1.11,<2.0); extra == "docs"
Requires-Dist: sphinx-rtd-theme (>=0.5,<0.6); extra == "docs"
Requires-Dist: tabulate (>=0.8.7,<0.9.0)
Requires-Dist: typing (>=3.7.4,<4.0.0)
Project-URL: Documentation, https://yager.readthedocs.io/en/latest/
Project-URL: Repository, https://github.com/undp/yager
Project-URL: issues, https://github.com/undp/yager/issues
